README.rst
setup.py
datasift/__init__.py
datasift/account.py
datasift/client.py
datasift/exceptions.py
datasift/historics.py
datasift/historics_preview.py
datasift/identity.py
datasift/limit.py
datasift/live_stream.py
datasift/managed_sources.py
datasift/odp.py
datasift/output_mapper.py
datasift/push.py
datasift/pylon.py
datasift/pylon_task.py
datasift/request.py
datasift/requests_ssl.py
datasift/token.py
datasift.egg-info/PKG-INFO
datasift.egg-info/SOURCES.txt
datasift.egg-info/dependency_links.txt
datasift.egg-info/requires.txt
datasift.egg-info/top_level.txt