Metadata-Version: 1.1
Name: datasift
Version: 2.12.0
Summary: The official DataSift API library for Python.
Home-page: https://github.com/datasift/datasift-python
Author: DataSift
Author-email: opensource@datasift.com
License: Copyright (C) 2012-Present by MediaSift Ltd. All Rights Reserved. See LICENSE for the full license.
Platform: UNKNOWN
Classifier: Development Status :: 4 - Beta
Classifier: Intended Audience :: Developers
Classifier: Operating System :: OS Independent
Classifier: Programming Language :: Python
Classifier: Programming Language :: Python :: 2.6
Classifier: Programming Language :: Python :: 2.7
Classifier: Programming Language :: Python :: 3.3
Classifier: Topic :: Software Development :: Libraries :: Python Modules
